gpao_utils/__init__.py
gpao_utils/gpao_test.py
gpao_utils/interface_utils.py
gpao_utils/store.py
gpao_utils/store_gui.py
gpao_utils/version.py
ign_gpao_utils-0.3.0.dist-info/LICENSE.md
ign_gpao_utils-0.3.0.dist-info/METADATA
ign_gpao_utils-0.3.0.dist-info/WHEEL
ign_gpao_utils-0.3.0.dist-info/top_level.txt
ign_gpao_utils-0.3.0.dist-info/RECORD
