Metadata-Version: 2.1
Name: ign-gpao-utils
Version: 0.3.0
Summary: Library used for build project with ign-gpao
Author-email: Léa Vauchier <lea.vauchier@ign.fr>, Guillaume Liégard <guillaume.liegard@ign.fr>, Yoann Apel <yoann.apel@ign.fr>, Elliot Luçon <elliot.lucon@ign.fr>
License-File: LICENSE.md
